README.md
setup.py
ImageDataSpliter.egg-info/PKG-INFO
ImageDataSpliter.egg-info/SOURCES.txt
ImageDataSpliter.egg-info/dependency_links.txt
ImageDataSpliter.egg-info/top_level.txt
imagedataspliter/Spliter.py
imagedataspliter/__init__.py