Metadata-Version: 2.4
Name: ImageDataSpliter
Version: 0.1.3
Summary: This utility splits an image dataset into train, validation, and test subsets while preserving the class folder structure.
Author: Volodymyr
Author-email: vova.dzimina@gmail.com
Requires-Python: >=3.8
Dynamic: author
Dynamic: author-email
Dynamic: description
Dynamic: description-content-type
Dynamic: requires-python
Dynamic: summary
